{
    "keep": {
        "days": true,
        "amount": 2
    },
    "auditLog": "C:\\Users\\user\\documents\\uride\\_uRide_Backend\\src\\logs\\.0902ee1ca36e0ecf06323d63c4b0434305c10c87-audit.json",
    "files": [
        {
            "date": 1741854252839,
            "name": "C:\\Users\\user\\documents\\uride\\_uRide_Backend\\src\\logs\\2025-03-13.log",
            "hash": "dfd3c892628d6039bd391237b2da86f3872194b90b4d0bae152ed849b383d715"
        },
        {
            "date": 1741941938430,
            "name": "C:\\Users\\user\\documents\\uride\\_uRide_Backend\\src\\logs\\2025-03-14.log",
            "hash": "e21ed1f02eb64b9237a8d55cc0fe56d6cfe8c22103242ec901729c403bb143aa"
        }
    ],
    "hashType": "sha256"
}